recaptchav3ninja/__init__.py
recaptchav3ninja/ninja.py
tempmailcreator/__init__.py
tempmailcreator/_mailer.py
tempmailcreator-1.0.2.dist-info/LICENSE
tempmailcreator-1.0.2.dist-info/METADATA
tempmailcreator-1.0.2.dist-info/WHEEL
tempmailcreator-1.0.2.dist-info/top_level.txt
tempmailcreator-1.0.2.dist-info/RECORD
