Metadata-Version: 2.1
Name: tempmailcreator
Version: 1.0.2
Summary: A flexible and customizable library for bypassing Google reCAPTCHA v3 challenges, with both synchronous and asynchronous support.
Home-page: https://github.com/70L0-0j0/Mailer
Author: 70L0-0j0
Author-email: 70L0-0j0@lamia.xyz
Classifier: Programming Language :: Python :: 3
Classifier: License :: OSI Approved :: MIT License
Classifier: Operating System :: OS Independent
Classifier: Intended Audience :: Developers
Classifier: Topic :: Software Development :: Libraries :: Python Modules
Requires-Python: >=3.6
License-File: LICENSE
Requires-Dist: requests
